[
  {
    "title": "A",
    "data": [
      { "name": "A-Contact 1", "photo": "https://picsum.photos/40" },
      { "name": "A-Contact 2", "photo": "https://picsum.photos/40" },
      { "name": "A-Contact 3", "photo": "https://picsum.photos/40" },
      { "name": "A-Contact 4", "photo": "https://picsum.photos/40" },
      { "name": "A-Contact 5", "photo": "https://picsum.photos/40" },
      { "name": "A-Contact 6", "photo": "https://picsum.photos/40" },
      { "name": "A-Contact 7", "photo": "https://picsum.photos/40" },
      { "name": "A-Contact 8", "photo": "https://picsum.photos/40" }
    ]
  },
  {
    "title": "B",
    "data": [
      { "name": "B-Contact 1", "photo": "https://picsum.photos/40" },
      { "name": "B-Contact 2", "photo": "https://picsum.photos/40" },
      { "name": "B-Contact 3", "photo": "https://picsum.photos/40" },
      { "name": "B-Contact 4", "photo": "https://picsum.photos/40" },
      { "name": "B-Contact 5", "photo": "https://picsum.photos/40" },
      { "name": "B-Contact 6", "photo": "https://picsum.photos/40" },
      { "name": "B-Contact 7", "photo": "https://picsum.photos/40" },
      { "name": "B-Contact 8", "photo": "https://picsum.photos/40" }
    ]
  },
  {
    "title": "C",
    "data": [
      { "name": "C-Contact 1", "photo": "https://picsum.photos/40" },
      { "name": "C-Contact 2", "photo": "https://picsum.photos/40" },
      { "name": "C-Contact 3", "photo": "https://picsum.photos/40" },
      { "name": "C-Contact 4", "photo": "https://picsum.photos/40" },
      { "name": "C-Contact 5", "photo": "https://picsum.photos/40" },
      { "name": "C-Contact 6", "photo": "https://picsum.photos/40" },
      { "name": "C-Contact 7", "photo": "https://picsum.photos/40" },
      { "name": "C-Contact 8", "photo": "https://picsum.photos/40" }
    ]
  },
  {
    "title": "D",
    "data": [
      { "name": "D-Contact 1", "photo": "https://picsum.photos/40" },
      { "name": "D-Contact 2", "photo": "https://picsum.photos/40" },
      { "name": "B-Contact 3", "photo": "https://picsum.photos/40" },
      { "name": "D-Contact 4", "photo": "https://picsum.photos/40" },
      { "name": "D-Contact 5", "photo": "https://picsum.photos/40" },
      { "name": "D-Contact 6", "photo": "https://picsum.photos/40" },
      { "name": "D-Contact 7", "photo": "https://picsum.photos/40" },
      { "name": "D-Contact 8", "photo": "https://picsum.photos/40" }
    ]
  },
  {
    "title": "E",
    "data": [
      { "name": "E-Contact 1", "photo": "https://picsum.photos/40" },
      { "name": "E-Contact 2", "photo": "https://picsum.photos/40" },
      { "name": "E-Contact 3", "photo": "https://picsum.photos/40" },
      { "name": "E-Contact 4", "photo": "https://picsum.photos/40" },
      { "name": "E-Contact 5", "photo": "https://picsum.photos/40" },
      { "name": "E-Contact 6", "photo": "https://picsum.photos/40" },
      { "name": "E-Contact 7", "photo": "https://picsum.photos/40" },
      { "name": "E-Contact 8", "photo": "https://picsum.photos/40" }
    ]
  },
  {
    "title": "F",
    "data": [
      { "name": "F-Contact 1", "photo": "https://picsum.photos/40" },
      { "name": "F-Contact 2", "photo": "https://picsum.photos/40" },
      { "name": "F-Contact 3", "photo": "https://picsum.photos/40" },
      { "name": "F-Contact 4", "photo": "https://picsum.photos/40" },
      { "name": "F-Contact 5", "photo": "https://picsum.photos/40" },
      { "name": "F-Contact 6", "photo": "https://picsum.photos/40" },
      { "name": "F-Contact 7", "photo": "https://picsum.photos/40" },
      { "name": "F-Contact 8", "photo": "https://picsum.photos/40" }
    ]
  },
  {
    "title": "G",
    "data": [
      { "name": "G-Contact 1", "photo": "https://picsum.photos/40" },
      { "name": "G-Contact 2", "photo": "https://picsum.photos/40" },
      { "name": "G-Contact 3", "photo": "https://picsum.photos/40" },
      { "name": "G-Contact 4", "photo": "https://picsum.photos/40" },
      { "name": "G-Contact 5", "photo": "https://picsum.photos/40" },
      { "name": "G-Contact 6", "photo": "https://picsum.photos/40" },
      { "name": "G-Contact 7", "photo": "https://picsum.photos/40" },
      { "name": "G-Contact 8", "photo": "https://picsum.photos/40" }
    ]
  },
  {
    "title": "H",
    "data": [
      { "name": "H-Contact 1", "photo": "https://picsum.photos/40" },
      { "name": "H-Contact 2", "photo": "https://picsum.photos/40" },
      { "name": "H-Contact 3", "photo": "https://picsum.photos/40" },
      { "name": "H-Contact 4", "photo": "https://picsum.photos/40" },
      { "name": "H-Contact 5", "photo": "https://picsum.photos/40" },
      { "name": "H-Contact 6", "photo": "https://picsum.photos/40" },
      { "name": "H-Contact 7", "photo": "https://picsum.photos/40" },
      { "name": "H-Contact 8", "photo": "https://picsum.photos/40" }
    ]
  },
  {
    "title": "I",
    "data": [
      { "name": "I-Contact 1", "photo": "https://picsum.photos/40" },
      { "name": "I-Contact 2", "photo": "https://picsum.photos/40" },
      { "name": "I-Contact 3", "photo": "https://picsum.photos/40" },
      { "name": "I-Contact 4", "photo": "https://picsum.photos/40" },
      { "name": "I-Contact 5", "photo": "https://picsum.photos/40" },
      { "name": "I-Contact 6", "photo": "https://picsum.photos/40" },
      { "name": "I-Contact 7", "photo": "https://picsum.photos/40" },
      { "name": "I-Contact 8", "photo": "https://picsum.photos/40" }
    ]
  },
  {
    "title": "J",
    "data": [
      { "name": "J-Contact 1", "photo": "https://picsum.photos/40" },
      { "name": "J-Contact 2", "photo": "https://picsum.photos/40" },
      { "name": "J-Contact 3", "photo": "https://picsum.photos/40" },
      { "name": "J-Contact 4", "photo": "https://picsum.photos/40" },
      { "name": "J-Contact 5", "photo": "https://picsum.photos/40" },
      { "name": "J-Contact 6", "photo": "https://picsum.photos/40" },
      { "name": "J-Contact 7", "photo": "https://picsum.photos/40" },
      { "name": "J-Contact 8", "photo": "https://picsum.photos/40" }
    ]
  },
  {
    "title": "K",
    "data": [
      { "name": "K-Contact 1", "photo": "https://picsum.photos/40" },
      { "name": "K-Contact 2", "photo": "https://picsum.photos/40" },
      { "name": "K-Contact 3", "photo": "https://picsum.photos/40" },
      { "name": "K-Contact 4", "photo": "https://picsum.photos/40" },
      { "name": "K-Contact 5", "photo": "https://picsum.photos/40" },
      { "name": "K-Contact 6", "photo": "https://picsum.photos/40" },
      { "name": "K-Contact 7", "photo": "https://picsum.photos/40" },
      { "name": "K-Contact 8", "photo": "https://picsum.photos/40" }
    ]
  },
  {
    "title": "L",
    "data": [
      { "name": "L-Contact 1", "photo": "https://picsum.photos/40" },
      { "name": "L-Contact 2", "photo": "https://picsum.photos/40" },
      { "name": "L-Contact 3", "photo": "https://picsum.photos/40" },
      { "name": "L-Contact 4", "photo": "https://picsum.photos/40" },
      { "name": "L-Contact 5", "photo": "https://picsum.photos/40" },
      { "name": "L-Contact 6", "photo": "https://picsum.photos/40" },
      { "name": "L-Contact 7", "photo": "https://picsum.photos/40" },
      { "name": "L-Contact 8", "photo": "https://picsum.photos/40" }
    ]
  },
  {
    "title": "M",
    "data": [
      { "name": "M-Contact 1", "photo": "https://picsum.photos/40" },
      { "name": "M-Contact 2", "photo": "https://picsum.photos/40" },
      { "name": "M-Contact 3", "photo": "https://picsum.photos/40" },
      { "name": "M-Contact 4", "photo": "https://picsum.photos/40" },
      { "name": "M-Contact 5", "photo": "https://picsum.photos/40" },
      { "name": "M-Contact 6", "photo": "https://picsum.photos/40" },
      { "name": "M-Contact 7", "photo": "https://picsum.photos/40" },
      { "name": "M-Contact 8", "photo": "https://picsum.photos/40" }
    ]
  },
  {
    "title": "N",
    "data": [
      { "name": "N-Contact 1", "photo": "https://picsum.photos/40" },
      { "name": "N-Contact 2", "photo": "https://picsum.photos/40" },
      { "name": "N-Contact 3", "photo": "https://picsum.photos/40" },
      { "name": "N-Contact 4", "photo": "https://picsum.photos/40" },
      { "name": "N-Contact 5", "photo": "https://picsum.photos/40" },
      { "name": "N-Contact 6", "photo": "https://picsum.photos/40" },
      { "name": "N-Contact 7", "photo": "https://picsum.photos/40" },
      { "name": "N-Contact 8", "photo": "https://picsum.photos/40" }
    ]
  },
  {
    "title": "O",
    "data": [
      { "name": "O-Contact 1", "photo": "https://picsum.photos/40" },
      { "name": "O-Contact 2", "photo": "https://picsum.photos/40" },
      { "name": "O-Contact 3", "photo": "https://picsum.photos/40" },
      { "name": "O-Contact 4", "photo": "https://picsum.photos/40" },
      { "name": "O-Contact 5", "photo": "https://picsum.photos/40" },
      { "name": "O-Contact 6", "photo": "https://picsum.photos/40" },
      { "name": "O-Contact 7", "photo": "https://picsum.photos/40" },
      { "name": "O-Contact 8", "photo": "https://picsum.photos/40" }
    ]
  },
  {
    "title": "P",
    "data": [
      { "name": "P-Contact 1", "photo": "https://picsum.photos/40" },
      { "name": "P-Contact 2", "photo": "https://picsum.photos/40" },
      { "name": "P-Contact 3", "photo": "https://picsum.photos/40" },
      { "name": "P-Contact 4", "photo": "https://picsum.photos/40" },
      { "name": "P-Contact 5", "photo": "https://picsum.photos/40" },
      { "name": "P-Contact 6", "photo": "https://picsum.photos/40" },
      { "name": "P-Contact 7", "photo": "https://picsum.photos/40" },
      { "name": "P-Contact 8", "photo": "https://picsum.photos/40" }
    ]
  },
  {
    "title": "Q",
    "data": [
      { "name": "Q-Contact 1", "photo": "https://picsum.photos/40" },
      { "name": "Q-Contact 2", "photo": "https://picsum.photos/40" },
      { "name": "Q-Contact 3", "photo": "https://picsum.photos/40" },
      { "name": "Q-Contact 4", "photo": "https://picsum.photos/40" },
      { "name": "Q-Contact 5", "photo": "https://picsum.photos/40" },
      { "name": "Q-Contact 6", "photo": "https://picsum.photos/40" },
      { "name": "Q-Contact 7", "photo": "https://picsum.photos/40" },
      { "name": "Q-Contact 8", "photo": "https://picsum.photos/40" }
    ]
  },
  {
    "title": "R",
    "data": [
      { "name": "R-Contact 1", "photo": "https://picsum.photos/40" },
      { "name": "R-Contact 2", "photo": "https://picsum.photos/40" },
      { "name": "R-Contact 3", "photo": "https://picsum.photos/40" },
      { "name": "R-Contact 4", "photo": "https://picsum.photos/40" },
      { "name": "R-Contact 5", "photo": "https://picsum.photos/40" },
      { "name": "R-Contact 6", "photo": "https://picsum.photos/40" },
      { "name": "R-Contact 7", "photo": "https://picsum.photos/40" },
      { "name": "R-Contact 8", "photo": "https://picsum.photos/40" }
    ]
  },
  {
    "title": "S",
    "data": [
      { "name": "S-Contact 1", "photo": "https://picsum.photos/40" },
      { "name": "S-Contact 2", "photo": "https://picsum.photos/40" },
      { "name": "S-Contact 3", "photo": "https://picsum.photos/40" },
      { "name": "S-Contact 4", "photo": "https://picsum.photos/40" },
      { "name": "S-Contact 5", "photo": "https://picsum.photos/40" },
      { "name": "S-Contact 6", "photo": "https://picsum.photos/40" },
      { "name": "S-Contact 7", "photo": "https://picsum.photos/40" },
      { "name": "S-Contact 8", "photo": "https://picsum.photos/40" }
    ]
  },
  {
    "title": "T",
    "data": [
      { "name": "T-Contact 1", "photo": "https://picsum.photos/40" },
      { "name": "T-Contact 2", "photo": "https://picsum.photos/40" },
      { "name": "T-Contact 3", "photo": "https://picsum.photos/40" },
      { "name": "T-Contact 4", "photo": "https://picsum.photos/40" },
      { "name": "T-Contact 5", "photo": "https://picsum.photos/40" },
      { "name": "T-Contact 6", "photo": "https://picsum.photos/40" },
      { "name": "T-Contact 7", "photo": "https://picsum.photos/40" },
      { "name": "T-Contact 8", "photo": "https://picsum.photos/40" }
    ]
  },
  {
    "title": "U",
    "data": [
      { "name": "U-Contact 1", "photo": "https://picsum.photos/40" },
      { "name": "U-Contact 2", "photo": "https://picsum.photos/40" },
      { "name": "U-Contact 3", "photo": "https://picsum.photos/40" },
      { "name": "U-Contact 4", "photo": "https://picsum.photos/40" },
      { "name": "U-Contact 5", "photo": "https://picsum.photos/40" },
      { "name": "U-Contact 6", "photo": "https://picsum.photos/40" },
      { "name": "U-Contact 7", "photo": "https://picsum.photos/40" },
      { "name": "U-Contact 8", "photo": "https://picsum.photos/40" }
    ]
  },
  {
    "title": "V",
    "data": [
      { "name": "V-Contact 1", "photo": "https://picsum.photos/40" },
      { "name": "V-Contact 2", "photo": "https://picsum.photos/40" },
      { "name": "V-Contact 3", "photo": "https://picsum.photos/40" },
      { "name": "V-Contact 4", "photo": "https://picsum.photos/40" },
      { "name": "V-Contact 5", "photo": "https://picsum.photos/40" },
      { "name": "V-Contact 6", "photo": "https://picsum.photos/40" },
      { "name": "V-Contact 7", "photo": "https://picsum.photos/40" },
      { "name": "V-Contact 8", "photo": "https://picsum.photos/40" }
    ]
  },
  {
    "title": "W",
    "data": [
      { "name": "W-Contact 1", "photo": "https://picsum.photos/40" },
      { "name": "W-Contact 2", "photo": "https://picsum.photos/40" },
      { "name": "W-Contact 3", "photo": "https://picsum.photos/40" },
      { "name": "W-Contact 4", "photo": "https://picsum.photos/40" },
      { "name": "W-Contact 5", "photo": "https://picsum.photos/40" },
      { "name": "W-Contact 6", "photo": "https://picsum.photos/40" },
      { "name": "W-Contact 7", "photo": "https://picsum.photos/40" },
      { "name": "W-Contact 8", "photo": "https://picsum.photos/40" }
    ]
  },
  {
    "title": "X",
    "data": [
      { "name": "X-Contact 1", "photo": "https://picsum.photos/40" },
      { "name": "X-Contact 2", "photo": "https://picsum.photos/40" },
      { "name": "X-Contact 3", "photo": "https://picsum.photos/40" },
      { "name": "X-Contact 4", "photo": "https://picsum.photos/40" },
      { "name": "X-Contact 5", "photo": "https://picsum.photos/40" },
      { "name": "X-Contact 6", "photo": "https://picsum.photos/40" },
      { "name": "X-Contact 7", "photo": "https://picsum.photos/40" },
      { "name": "X-Contact 8", "photo": "https://picsum.photos/40" }
    ]
  },
  {
    "title": "Y",
    "data": [
      { "name": "Y-Contact 1", "photo": "https://picsum.photos/40" },
      { "name": "Y-Contact 2", "photo": "https://picsum.photos/40" },
      { "name": "Y-Contact 3", "photo": "https://picsum.photos/40" },
      { "name": "Y-Contact 4", "photo": "https://picsum.photos/40" },
      { "name": "Y-Contact 5", "photo": "https://picsum.photos/40" },
      { "name": "Y-Contact 6", "photo": "https://picsum.photos/40" },
      { "name": "Y-Contact 7", "photo": "https://picsum.photos/40" },
      { "name": "Y-Contact 8", "photo": "https://picsum.photos/40" }
    ]
  },
  {
    "title": "Z",
    "data": [
      { "name": "Z-Contact 1", "photo": "https://picsum.photos/40" },
      { "name": "Z-Contact 2", "photo": "https://picsum.photos/40" },
      { "name": "Z-Contact 3", "photo": "https://picsum.photos/40" },
      { "name": "Z-Contact 4", "photo": "https://picsum.photos/40" },
      { "name": "Z-Contact 5", "photo": "https://picsum.photos/40" },
      { "name": "Z-Contact 6", "photo": "https://picsum.photos/40" },
      { "name": "Z-Contact 7", "photo": "https://picsum.photos/40" },
      { "name": "Z-Contact 8", "photo": "https://picsum.photos/40" }
    ]
  }
]